devlibx_avro_helper/month_data.py
devlibx_avro_helper/month_data_v1.py
devlibx_avro_helper/test_month_data.py
devlibx_avro_helper/test_month_data_v1.py
avro_helper_devlibx-0.2.3.dist-info/METADATA
avro_helper_devlibx-0.2.3.dist-info/WHEEL
avro_helper_devlibx-0.2.3.dist-info/top_level.txt
avro_helper_devlibx-0.2.3.dist-info/RECORD
